types_vobject-0.9.9.20250601.dist-info/licenses/LICENSE
vobject-stubs/METADATA.toml
vobject-stubs/__init__.pyi
vobject-stubs/base.pyi
vobject-stubs/behavior.pyi
vobject-stubs/change_tz.pyi
vobject-stubs/hcalendar.pyi
vobject-stubs/icalendar.pyi
vobject-stubs/ics_diff.pyi
vobject-stubs/py.typed
vobject-stubs/vcard.pyi
vobject-stubs/win32tz.pyi
types_vobject-0.9.9.20250601.dist-info/METADATA
types_vobject-0.9.9.20250601.dist-info/WHEEL
types_vobject-0.9.9.20250601.dist-info/top_level.txt
types_vobject-0.9.9.20250601.dist-info/RECORD
